sigkan/__init__.py
sigkan/grns.py
sigkan/sigkan.py
sigkan-0.2.0.dist-info/METADATA
sigkan-0.2.0.dist-info/WHEEL
sigkan-0.2.0.dist-info/RECORD
