Metadata-Version: 2.1
Name: sigkan
Version: 0.2.0
Summary: Path Signature-Weighted Kolmogorov-Arnold Networks for Time Series
Author: Rémi Genet
Requires-Python: >=3.9,<3.13
Classifier: Programming Language :: Python :: 3
Classifier: Programming Language :: Python :: 3.9
Classifier: Programming Language :: Python :: 3.10
Classifier: Programming Language :: Python :: 3.11
Classifier: Programming Language :: Python :: 3.12
Requires-Dist: keras (>=3.0.0,<4.0.0)
Requires-Dist: keras_efficient_kan (>=0.1.9,<0.2.0)
Requires-Dist: keras_sig (>=1.0.0,<2.0.0)
Requires-Dist: numpy (>=2.0.0,<3.0.0)
